docs2llm/__init__.py
docs2llm/cli.py
docs2llm/main.py
docs2llm-0.1.0.dist-info/METADATA
docs2llm-0.1.0.dist-info/WHEEL
docs2llm-0.1.0.dist-info/entry_points.txt
docs2llm-0.1.0.dist-info/licenses/LICENSE
docs2llm-0.1.0.dist-info/RECORD
