Metadata-Version: 2.4
Name: docs2llm
Version: 0.1.0
Summary: CLI tool to generate LLM context from documentation.
Author: nklsw
License-File: LICENSE
Requires-Python: >=3.11
Requires-Dist: beautifulsoup4>=4.13.3
Requires-Dist: click>=8.1.7
Requires-Dist: markdown>=3.8
Requires-Dist: requests>=2.32.3
Requires-Dist: rich>=13.7.0
